minnwest_pipeline_test/__init__.py
minnwest_pipeline_test/api/__init__.py
minnwest_pipeline_test/api/account/__init__.py
minnwest_pipeline_test/api/account/post_api_v_1_q_2_account_view_transfers.py
minnwest_pipeline_test/api/auth/__init__.py
minnwest_pipeline_test/api/auth/get_api_v_1_q_2_auth_check.py
minnwest_pipeline_test/api/auth/post_api_v_1_q_2_auth_login.py
minnwest_pipeline_test/api/auth/post_api_v_1_q_2_auth_refresh.py
minnwest_pipeline_test/api/portfolio/__init__.py
minnwest_pipeline_test/api/portfolio/post_api_v_1_q_2_portfolio_view_transfers.py
minnwest_pipeline_test/client.py
minnwest_pipeline_test/errors.py
minnwest_pipeline_test/models/__init__.py
minnwest_pipeline_test/models/account_transfer_view_request.py
minnwest_pipeline_test/models/account_type.py
minnwest_pipeline_test/models/boolean_api_result.py
minnwest_pipeline_test/models/login_model.py
minnwest_pipeline_test/models/portfolio_transfer_view_request.py
minnwest_pipeline_test/models/problem_details.py
minnwest_pipeline_test/models/soa_account.py
minnwest_pipeline_test/models/soa_account_api_result.py
minnwest_pipeline_test/models/soa_account_list_api_result.py
minnwest_pipeline_test/models/soa_transfer.py
minnwest_pipeline_test/models/token_model.py
minnwest_pipeline_test/models/token_model_api_result.py
minnwest_pipeline_test/models/transfer_credit_type.py
minnwest_pipeline_test/models/transfer_frequency.py
minnwest_pipeline_test/models/validation_problem_details.py
minnwest_pipeline_test/models/validation_problem_details_errors_type_0.py
minnwest_pipeline_test/py.typed
minnwest_pipeline_test/types.py
minnwest_pipeline_test-1.0.1.dist-info/METADATA
minnwest_pipeline_test-1.0.1.dist-info/WHEEL
minnwest_pipeline_test-1.0.1.dist-info/RECORD
